to_upper_gate.v
`timescale 1ns / 1ps

// to_upper_gate.v
// Author: Nadim Siddique
// Project 1 – toUpper() Function Using Primitive Gates

  module to_upper_gate(ascii_in, ascii_out);
  input [7:0] ascii_in;
  output [7:0] ascii_out;

  wire [0:4] F_terms;
  wire a_in_6_prime;
  wire [7:0] ascii_in_prime;

   // Inverters 
  not #5 not1 (ascii_in_prime[6] , ascii_in[6]);
  not #5 not2 (ascii_in_prime[4] , ascii_in[4]);
  not #5 not3 (ascii_in_prime[3] , ascii_in[3]);
  not #5 not4 (ascii_in_prime[2] , ascii_in[2]);
  not #5 not5 (ascii_in_prime[1] , ascii_in[1]);
  not #5 not6 (ascii_in_prime[0] , ascii_in[0]);
  not #5 not7 (ascii_in_prime[7] , ascii_in[7]);
  not #5 not8 (ascii_in_prime[5] , ascii_in[5]);


  and #10 and1 (F_terms[0], ascii_in[5], ascii_in[7]);
  and #10 and2 (F_terms[1], ascii_in[5], ascii_in_prime[6], ascii_in_prime[7]);
  and #10 and3 (F_terms[2], ascii_in_prime[7], ascii_in[6], ascii_in[5], ascii_in[4], ascii_in[3], ascii_in[2]);
  and #10 and4 (F_terms[3], ascii_in_prime[7], ascii_in[5], ascii_in_prime[4], ascii_in_prime[3], ascii_in_prime[2], ascii_in_prime[1], ascii_in_prime[0]);
  and #10 and5 (F_terms[4], ascii_in_prime[7], ascii_in[6], ascii_in[5], ascii_in[4],  ascii_in[3], ascii_in_prime[2],  ascii_in[1], ascii_in[0]);
  or #10 or1 (ascii_out[5], F_terms[0], F_terms[1], F_terms[2], F_terms[3], F_terms[4]);


  assign ascii_out[7:6] = ascii_in[7:6];
  assign ascii_out[4:0] = ascii_in[4:0];

endmodule

tb_to_upper.v
`timescale 1ns / 1ps

// tb_to_upper.v
// Author: Nadim Siddique
// Project 1 – toUpper() Function Using Primitive Gates

module tb_to_upper;
  reg  [7:0] ascii_in;
  wire [7:0] ascii_out;

// Change the DELAY value below to test timing thresholds.
//   25 ns → Correct operation (Screenshot A)
//   20 ns → Threshold (may still pass)
//   15 ns or below → Failure (Screenshot B)
  integer DELAY = 15;

  to_upper_gate DUT(.ascii_in(ascii_in), .ascii_out(ascii_out));

  // print for char (shows hex and ASCII)
  task show_io;
    begin
      $display("[%0t ns] IN=0x%0h (%0d) %s  OUT=0x%0h (%0d) %s",
               $time, ascii_in, ascii_in, printable(ascii_in), ascii_out, ascii_out, printable(ascii_out));
    end
  endtask

  function [8*4:1] printable; 
    input [7:0] x;
    begin
      if (x >= 8'd32 && x <= 8'd126) printable = {"'", x[7:0], "' "};
      else printable = "    ";
    end
  endfunction

  initial begin
    $dumpfile("to_upper.vcd");
    $dumpvars(0, tb_to_upper);

    ascii_in = 8'h00;

    //testset 
    drive(8'd40);   // '('
    drive(8'd72);   // 'H'
    drive(8'd183);  // ·
    drive(8'd131);  // ƒ
    drive(8'd124);  // '|'
    drive(8'd20);   // DC4
    drive(8'd235);  // ë
    drive(8'd97);   // 'a'  -> 'A'
    drive(8'd65);   // 'A'
    drive(8'd122);  // 'z'  -> 'Z'
    drive(8'd71);   // 'G'
    drive(8'd109);  // 'm'  -> 'M'
    drive(8'd146);  // '
    drive(8'd48);   // '0'
    drive(8'd207);  // Ï
    drive(8'd58);   // ':'
    drive(8'd123);  // '{'
    drive(8'd148);  // ”
    drive(8'd127);  // DEL

  
    #(5*DELAY);
    $finish;
  end

  task drive(input [7:0] val);
    begin
      ascii_in = val;
      #(DELAY);
      show_io();
    end
  endtask

endmodule

to_upper.vcd
$date
	Thu Nov 06 16:21:27 2025
$end
$version
	Icarus Verilog
$end
$timescale
	1ps
$end
$scope module tb_to_upper $end
$var wire 8 ! ascii_out [7:0] $end
$var reg 8 " ascii_in [7:0] $end
$var integer 32 # DELAY [31:0] $end
$scope function printable $end
$var reg 8 $ x [7:0] $end
$upscope $end
$scope module DUT $end
$var wire 8 % ascii_in [7:0] $end
$var wire 8 & ascii_out [7:0] $end
$var wire 8 ' ascii_in_prime [7:0] $end
$var wire 5 ( F_terms [0:4] $end
$upscope $end
$scope task drive $end
$var reg 8 ) val [7:0] $end
$upscope $end
$scope task show_io $end
$upscope $end
$upscope $end
$enddefinitions $end
$comment Show the parameter values. $end
$dumpall
$end
#0
$dumpvars
b101000 )
bx (
bx '
b0x01000 &
b101000 %
bx $
b1111 #
b101000 "
b0x01000 !
$end
#5000
b11010111 '
#10000
b0x0x0 (
#15000
b1x01000 !
b1x01000 &
b1000 (
b1001000 "
b1001000 %
b1001000 )
b0x01000 $
#20000
b10110111 '
#25000
b1101000 !
b1101000 &
b0 (
#30000
b10110111 !
b10110111 &
b10110111 "
b10110111 %
b10110111 )
b1101000 $
#35000
b1001000 '
b10010111 !
b10010111 &
#40000
b10000 (
#45000
b10000011 !
b10000011 &
b10000011 "
b10000011 %
b10000011 )
b10010111 $
#50000
b1111100 '
b10100011 !
b10100011 &
#55000
b0 (
#60000
b1111100 !
b1111100 &
b1111100 "
b1111100 %
b1111100 )
b10100011 $
#65000
b10000011 '
b1011100 !
b1011100 &
#75000
b10100 !
b10100 &
b100 (
b10100 "
b10100 %
b10100 )
b1011100 $
#80000
b11101011 '
#85000
b110100 !
b110100 &
b0 (
#90000
b11101011 !
b11101011 &
b11101011 "
b11101011 %
b11101011 )
b110100 $
#95000
b10100 '
b11001011 !
b11001011 &
#100000
b10000 (
#105000
b1000001 !
b1000001 &
b1100001 "
b1100001 %
b1100001 )
b11001011 $
#110000
b10011110 '
b1100001 !
b1100001 &
#115000
b0 (
#120000
b1000001 "
b1000001 %
b1000001 )
b1100001 $
#125000
b10111110 '
b1000001 !
b1000001 &
#135000
b1011010 !
b1011010 &
b1111010 "
b1111010 %
b1111010 )
b1000001 $
#140000
b10000101 '
#150000
b1000111 !
b1000111 &
b1000111 "
b1000111 %
b1000111 )
b1011010 $
#155000
b10111000 '
#165000
b1001101 !
b1001101 &
b1101101 "
b1101101 %
b1101101 )
b1000111 $
#170000
b10010010 '
#180000
b10010010 !
b10010010 &
b10010010 "
b10010010 %
b10010010 )
b1001101 $
#185000
b1101101 '
#195000
b10000 !
b10000 &
b110000 "
b110000 %
b110000 )
b10010010 $
#200000
b11001111 '
#210000
b11001111 !
b11001111 &
b1000 (
b11001111 "
b11001111 %
b11001111 )
b10000 $
#215000
b110000 '
#220000
b11101111 !
b11101111 &
b0 (
#225000
b111010 !
b111010 &
b111010 "
b111010 %
b111010 )
b11101111 $
#230000
b11000101 '
b11010 !
b11010 &
#240000
b1011011 !
b1011011 &
b1000 (
b1111011 "
b1111011 %
b1111011 )
b11010 $
#245000
b10000100 '
#250000
b1111011 !
b1111011 &
b1001 (
#255000
b10110100 !
b10110100 &
b1 (
b10010100 "
b10010100 %
b10010100 )
b1111011 $
#260000
b1101011 '
#265000
b0 (
#270000
b1111111 !
b1111111 &
b1111111 "
b1111111 %
b1111111 )
b10110100 $
#275000
b10000000 '
b1011111 !
b1011111 &
#285000
b100 (
b1011111 $
#295000
b1111111 !
b1111111 &
